{"users":[{"path":"a,c,b,e","pass":"arko","username":"arko"},{"path":"e,d,c,a","pass":"ko","username":"ko"},{"path":"a,b,c,d","pass":"arko","username":"arko"},{"path":"a,b,c,d","pass":"arko","username":"arko"},{"path":"d,c,a,b,e","pass":"ko1234","username":"ko1234"},{"path":"d,c,a,b,e","pass":"ko1234","username":"ko1234"},{"path":"a,c,d","pass":"arko","username":"arko"},{"path":"a,b,c,d","pass":"arko","username":"arko"},{"path":"a,b,c,d","pass":"arko","username":"arko"},{"path":"a,b,e,d","pass":"arko","username":"arko"},{"path":"a,b,e,d","pass":"arko","username":"arko"},{"path":"a,b,e,d","pass":"arko","username":"arko"},{"path":"a,b,c,d","pass":"arko","username":"arko"},{"path":"e,b,a","pass":"arko","username":"arko"},{"path":"a,b,c,d,e","pass":"arko","username":"arko"},{"path":"e,d,c,b,a","pass":"arko","username":"arko"},{"path":"e,b,c,d,c,d,c,a","pass":"arko","username":"arko"},{"path":"e,b,c,d,c,a","pass":"arko","username":"arko"},{"path":"a,b,c","pass":"arko","username":"arko"},{"path":"a,b,e,b,c,d","pass":"arko","username":"arko"},{"path":"a,c,d","pass":"arko","username":"arko"},{"path":"a,b,c,d","pass":"arko","username":"arko"},{"path":"a,b,a,e,d","pass":"arko","username":"arko"},{"path":"a,c,b,e,d","pass":"arko","username":"arko"},{"path":"a,c,b,e,d","pass":"arko","username":"arko"},{"path":"a,b,c,d","pass":"arko","username":"arko"},{"path":"a,b,c,d","pass":"arko","username":"arko"},{"path":"a,b,c,b,e,b,e,b,e,d","pass":"arko","username":"arko"},{"path":"a,b,e,b,c,d","pass":"arko","username":"arko"},{"path":"a,c,b,e,d","pass":"arko","username":"arko"},{"path":"","pass":"KO1234","username":"KO"},{"path":"e,d,c,a","pass":"ko","username":"ko"},{"path":"a,c,b,e","pass":"arko","username":"arko"}]}